sober_scan/__init__.py
sober_scan/cli.py
sober_scan/config.py
sober_scan/dataset_management.py
sober_scan/feature_extraction.py
sober_scan/model_management.py
sober_scan/utils.py
sober_scan/commands/__init__.py
sober_scan/commands/detect.py
sober_scan/commands/evaluate.py
sober_scan/commands/manage.py
sober_scan/commands/model.py
sober_scan/commands/train.py
sober_scan/models/cnn.py
sober_scan/models/knn.py
sober_scan/models/nb.py
sober_scan/models/rf.py
sober_scan/models/svm.py
sober_scan/tests/__init__.py
sober_scan/tests/test_cli.py
sober_scan-0.0.5.dist-info/METADATA
sober_scan-0.0.5.dist-info/WHEEL
sober_scan-0.0.5.dist-info/entry_points.txt
sober_scan-0.0.5.dist-info/licenses/LICENSE
sober_scan-0.0.5.dist-info/RECORD
