Metadata-Version: 2.4
Name: sober-scan
Version: 0.0.5
Summary: A CLI tool that detects alcohol intoxication from facial images.
Project-URL: Homepage, https://github.com/Sang-Buster/Sober-Scan
Project-URL: Documentation, https://deepwiki.com/Sang-Buster/Sober-Scan
Project-URL: Repository, https://github.com/Sang-Buster/Sober-Scan
Author-email: Sang Buster <hello@singsongaftermath.com>
License: MIT License
License-File: LICENSE
Requires-Python: >=3.10
Requires-Dist: click<8.1.0
Requires-Dist: dlib>=19.24.8
Requires-Dist: joblib>=1.5.0
Requires-Dist: matplotlib>=3.10.3
Requires-Dist: numpy>=2.2.5
Requires-Dist: opencv-python>=4.11.0.86
Requires-Dist: pandas>=2.2.3
Requires-Dist: scikit-learn>=1.6.1
Requires-Dist: torch>=2.7.0
Requires-Dist: torchvision>=0.22.0
Requires-Dist: typer>=0.15.3
